{
  "_help": "Codis apresos amb els scripts (scripts/learn-rf.js per a la llum RF, scripts/learn-ir.js per a l'AC IR), en hexadecimal. Una cadena buida vol dir 'encara no après'. A la secció 'llum' pots afegir/canviar claus lliurement: cada codi no buit apareix com a botó al panell automàticament.",
  "llum": {
    "power_toggle": "",
    "light_toggle": "",
    "brightness_up": "",
    "brightness_down": "",
    "color_temp_warm": "",
    "color_temp_cool": "",
    "night_mode_warm": "",
    "sleep_mode": "",
    "confirm_select": ""
  },
  "ac": {
    "ac_off": "",
    "ac_cool_22": "",
    "ac_cool_23": "",
    "ac_cool_24": "",
    "ac_cool_25": "",
    "ac_cool_26": ""
  }
}
